flask_eventdispatcher.py
flask_eventdispatcher-0.2.0.dist-info/WHEEL
flask_eventdispatcher-0.2.0.dist-info/METADATA
flask_eventdispatcher-0.2.0.dist-info/RECORD
